{
  "_id": "31mYJ4ZjbnHdzWAmjJ4UcCQJ6iA",
  "_type": "PokemonCard",
  "_index": "b1v",
  "title": "Petilil",
  "number": "6",
  "edgeColor": "#97999b",
  "rarity": "common",
  "cardtype": "pokemon",
  "hp": 60,
  "energy": "grass",
  "stage": "basic",
  "pokemon": {
    "_id": "36pVn8cptOZzZNupnmN1oqLKcYR",
    "_type": "entry",
    "_entry": "36dmGRgQw8eOqn0g4zg98NcmkZ2"
  },
  "illustrator": {
    "_id": "33w1towjEvL5UA2CLNW4lSBejoJ",
    "_type": "entry",
    "_entry": "33vX8g7E93SP7mdGCul4kxGJigv"
  },
  "card": {
    "_id": "31mYL11p4KbAjCFmwmfMyqcj0li",
    "_type": "image",
    "_entry": "31mYGLcojtMfq7RbB2RhOU8RHqy"
  },
  "reverseCard": {},
  "variants": [
    {
      "_id": "31mYJ4BNucqSqmFPRLRTIjVauKR",
      "_index": "a0",
      "_type": "Variant",
      "variant": "normal",
      "pattern": null,
      "mask": {},
      "foil": {}
    },
    {
      "_id": "31mYc6W3Z512zmBOdm86ifHRCok",
      "_index": "a1",
      "_type": "Variant",
      "variant": "reverse_holofoil",
      "mask": {
        "_id": "31mYqfFGoxXUzhTwX21Oqnn6qEI",
        "_type": "image",
        "_entry": "31mYpANYqzAbGVAbOjtFZQMxPDZ"
      },
      "foil": {
        "_id": "31mYrUYO5gVV7WvwABuKS6mShuq",
        "_type": "image",
        "_entry": "31mYp7qjwRcgQhemUSkQpvr4rCA"
      }
    },
    {
      "_id": "31mYcekdSbvIlUO76kIR5xbPx8Z",
      "_index": "a2",
      "_type": "Variant",
      "variant": "reverse_holofoil",
      "pattern": "pokeBall",
      "mask": {},
      "foil": {}
    },
    {
      "_id": "31mYdjY1oaVAWChanpTM9yiuok0",
      "_index": "a3",
      "_type": "Variant",
      "variant": "reverse_holofoil",
      "pattern": "masterBall",
      "mask": {},
      "foil": {}
    }
  ]
}